LICENSE
README.md
setup.py
easyio/__init__.py
easyio/__version__.py
easyio/base/__init__.py
easyio/base/reader.py
easyio/base/utils.py
easyio/base/writer.py
easyio/command/__init__.py
easyio/excel/__init__.py
easyio/excel/reader.py
easyio/excel/tests/__init__.py
easyio/excel/tests/test_reader.py
py_easyio.egg-info/PKG-INFO
py_easyio.egg-info/SOURCES.txt
py_easyio.egg-info/dependency_links.txt
py_easyio.egg-info/not-zip-safe
py_easyio.egg-info/requires.txt
py_easyio.egg-info/top_level.txt