Metadata-Version: 2.1
Name: py-easyio
Version: 0.0.2
Summary: A simple and easy way to read and write excel files.
Home-page: https://github.com/iiicebearrr/easy-io
Author: Icebear
Author-email: 969549808@qq.com
License: Apache 2.0
Project-URL: Source, https://github.com/iiicebearrr/easy-io
Classifier: License :: OSI Approved :: Apache Software License
Classifier: Operating System :: OS Independent
Classifier: Programming Language :: Python
Classifier: Programming Language :: Python :: 3.10
Classifier: Programming Language :: Python :: 3.11
Classifier: Programming Language :: Python :: 3 :: Only
Requires-Python: >=3.10,<4
License-File: LICENSE
